[
    {
        "title" : "客户服务",
        "con" : ["服务声明","常见问题","售后服务","配送说明","配送范围","订单查询","取消订单","补交货款","隐私条款","安全条款"]

    },
    {
        "title" : "热门资讯",
        "con" : ["中国鲜花礼品网购物流程","中国鲜花礼品网订购演示","鲜花网能配送哪些城市？","鲜花售后服务是怎么样的？","我应该提前多久预订鲜花？"]

    },
    {
        "title" : "同城鲜花专区",
        "con" : ["深圳鲜花","广州鲜花","上海鲜花","北京鲜花","天津鲜花","重庆鲜花","成都鲜花","西安鲜花","武汉鲜花","南京鲜花","厦门鲜花","更多城市"]

    },
    {
        "title" : "联系我们",
        "con" : ["全国订购热线：400-889-8188(免长途费)","E-mail: kefu@hua.com","7x24小时在线订购","客服工作时间：8:30-21:00","在线客服"]
    }
]